earchive/__init__.py
earchive/__main__.py
earchive/commands/analyze.py
earchive/commands/check/__init__.py
earchive/commands/check/check.py
earchive/commands/check/config/__init__.py
earchive/commands/check/config/cast.py
earchive/commands/check/config/config.py
earchive/commands/check/config/default.py
earchive/commands/check/config/fs.py
earchive/commands/check/config/names.py
earchive/commands/check/config/os.py
earchive/commands/check/config/parse.py
earchive/commands/check/config/substitution.py
earchive/commands/check/names.py
earchive/commands/check/print.py
earchive/commands/check/utils.py
earchive/commands/cli.py
earchive/commands/compare.py
earchive/commands/copy.py
earchive/commands/md5.py
earchive/commands/repair.py
earchive/doc/__init__.py
earchive/doc/check.py
earchive/doc/doc.py
earchive/doc/utils.py
earchive/errors.py
earchive/lib/typer/__init__.py
earchive/lib/typer/__main__.py
earchive/lib/typer/_completion_classes.py
earchive/lib/typer/_completion_shared.py
earchive/lib/typer/_typing.py
earchive/lib/typer/cli.py
earchive/lib/typer/colors.py
earchive/lib/typer/completion.py
earchive/lib/typer/core.py
earchive/lib/typer/main.py
earchive/lib/typer/models.py
earchive/lib/typer/params.py
earchive/lib/typer/py.typed
earchive/lib/typer/rich_utils.py
earchive/lib/typer/testing.py
earchive/lib/typer/utils.py
earchive/main.py
earchive/names.py
earchive/py.typed
earchive/utils/fs.py
earchive/utils/os.py
earchive/utils/path.py
earchive/utils/progress.py
earchive/utils/toml.py
earchive/utils/tree.py
earchive-0.3.1.dist-info/LICENSE
earchive-0.3.1.dist-info/METADATA
earchive-0.3.1.dist-info/WHEEL
earchive-0.3.1.dist-info/entry_points.txt
earchive-0.3.1.dist-info/RECORD
